streamlit_drawable_canvas/__init__.py
streamlit_drawable_canvas/frontend/build/asset-manifest.json
streamlit_drawable_canvas/frontend/build/index.html
streamlit_drawable_canvas/frontend/build/static/css/main.8802268d.chunk.css
streamlit_drawable_canvas/frontend/build/static/css/main.8802268d.chunk.css.map
streamlit_drawable_canvas/frontend/build/static/js/2.1abb329b.chunk.js
streamlit_drawable_canvas/frontend/build/static/js/2.1abb329b.chunk.js.LICENSE.txt
streamlit_drawable_canvas/frontend/build/static/js/2.1abb329b.chunk.js.map
streamlit_drawable_canvas/frontend/build/static/js/main.ba92d802.chunk.js
streamlit_drawable_canvas/frontend/build/static/js/main.ba92d802.chunk.js.map
streamlit_drawable_canvas/frontend/build/static/js/runtime-main.3def19be.js
streamlit_drawable_canvas/frontend/build/static/js/runtime-main.3def19be.js.map
streamlit_drawable_canvas_bogaczm-0.9.4.dist-info/licenses/LICENSE
streamlit_drawable_canvas_bogaczm-0.9.4.dist-info/METADATA
streamlit_drawable_canvas_bogaczm-0.9.4.dist-info/WHEEL
streamlit_drawable_canvas_bogaczm-0.9.4.dist-info/top_level.txt
streamlit_drawable_canvas_bogaczm-0.9.4.dist-info/RECORD
